pygfile/__init__.py
pygfile/enc.py
pygfile/encfile.py
pygfile/unencfile.py
pygfile-0.0.7.dist-info/METADATA
pygfile-0.0.7.dist-info/WHEEL
pygfile-0.0.7.dist-info/top_level.txt
pygfile-0.0.7.dist-info/RECORD
